strawberry_input_extensions/__init__.py
strawberry_input_extensions/builtin.py
strawberry_input_extensions/exceptions.py
strawberry_input_extensions/extension.py
strawberry_input_extensions-0.0.2.dist-info/licenses/LICENSE
strawberry_input_extensions-0.0.2.dist-info/METADATA
strawberry_input_extensions-0.0.2.dist-info/WHEEL
strawberry_input_extensions-0.0.2.dist-info/top_level.txt
strawberry_input_extensions-0.0.2.dist-info/RECORD
