Metadata-Version: 2.4
Name: strawberry-input-extensions
Version: 0.0.2
Summary: Strawberry GraphQL input validation/transformation extensions
Author-email: Michael Thomas <michael@metatick.net>
License-Expression: MIT
Project-URL: Repository, https://github.com/metatick/strawberry-input-extensions
Project-URL: Documentation, https://github.com/metatick/strawberry-input-extensions
Keywords: graphql,strawberry-graphql
Requires-Python: <4.0,>=3.9
License-File: LICENSE
Requires-Dist: strawberry-graphql>=0.275.4
Dynamic: license-file
